{
  "annotations": {
    "list": [
      {
        "builtIn": 1,
        "datasource": {
          "type": "grafana",
          "uid": "-- Grafana --"
        },
        "enable": true,
        "hide": true,
        "iconColor": "rgba(0, 211, 255, 1)",
        "name": "Annotations & Alerts",
        "type": "dashboard"
      }
    ]
  },
  "editable": true,
  "fiscalYearStartMonth": 0,
  "graphTooltip": 0,
  "id": 35,
  "links": [],
  "panels": [
    {
      "datasource": {
        "type": "prometheus",
        "uid": "prometheus"
      },
      "fieldConfig": {
        "defaults": {
          "color": {
            "mode": "palette-classic"
          },
          "custom": {
            "axisBorderShow": false,
            "axisCenteredZero": false,
            "axisColorMode": "text",
            "axisLabel": "",
            "axisPlacement": "auto",
            "barAlignment": 0,
            "barWidthFactor": 0.6,
            "drawStyle": "line",
            "fillOpacity": 0,
            "gradientMode": "none",
            "hideFrom": {
              "legend": false,
              "tooltip": false,
              "viz": false
            },
            "insertNulls": false,
            "lineInterpolation": "linear",
            "lineWidth": 1,
            "pointSize": 5,
            "scaleDistribution": {
              "type": "linear"
            },
            "showPoints": "auto",
            "spanNulls": false,
            "stacking": {
              "group": "A",
              "mode": "none"
            },
            "thresholdsStyle": {
              "mode": "off"
            }
          },
          "links": [
            {
              "targetBlank": true,
              "title": "Explore correlated time series",
              "url": "d/explore-metrics/explore-metrics?var-Metric=${__field.labels.__name__}&var-tsspec=${__series.name}"
            }
          ],
          "mappings": [],
          "thresholds": {
            "mode": "absolute",
            "steps": [
              {
                "color": "green",
                "value": null
              },
              {
                "color": "red",
                "value": 80
              }
            ]
          }
        },
        "overrides": []
      },
      "gridPos": {
        "h": 8,
        "w": 12,
        "x": 0,
        "y": 0
      },
      "id": 8,
      "options": {
        "legend": {
          "calcs": [],
          "displayMode": "list",
          "placement": "bottom",
          "showLegend": true
        },
        "tooltip": {
          "hideZeros": false,
          "mode": "single",
          "sort": "none"
        }
      },
      "pluginVersion": "11.5.2",
      "targets": [
        {
          "disableTextWrap": false,
          "editorMode": "builder",
          "expr": "apache_request_duration_ms:avg1m",
          "fullMetaSearch": false,
          "includeNullMetadata": true,
          "legendFormat": "__auto",
          "range": true,
          "refId": "A",
          "useBackend": false
        },
        {
          "datasource": {
            "type": "prometheus",
            "uid": "prometheus"
          },
          "disableTextWrap": false,
          "editorMode": "builder",
          "expr": "apache_load{interval=\"1min\"}",
          "fullMetaSearch": false,
          "hide": false,
          "includeNullMetadata": true,
          "instant": false,
          "legendFormat": "__auto",
          "range": true,
          "refId": "B",
          "useBackend": false
        }
      ],
      "title": "Apache",
      "type": "timeseries"
    },
    {
      "datasource": {
        "type": "prometheus",
        "uid": "prometheus"
      },
      "fieldConfig": {
        "defaults": {
          "color": {
            "mode": "palette-classic"
          },
          "custom": {
            "axisBorderShow": false,
            "axisCenteredZero": false,
            "axisColorMode": "text",
            "axisLabel": "",
            "axisPlacement": "auto",
            "barAlignment": 0,
            "barWidthFactor": 0.6,
            "drawStyle": "line",
            "fillOpacity": 0,
            "gradientMode": "none",
            "hideFrom": {
              "legend": false,
              "tooltip": false,
              "viz": false
            },
            "insertNulls": false,
            "lineInterpolation": "linear",
            "lineWidth": 1,
            "pointSize": 5,
            "scaleDistribution": {
              "type": "linear"
            },
            "showPoints": "auto",
            "spanNulls": false,
            "stacking": {
              "group": "A",
              "mode": "none"
            },
            "thresholdsStyle": {
              "mode": "off"
            }
          },
          "links": [
            {
              "targetBlank": true,
              "title": "Explore correlated time series",
              "url": "d/explore-metrics/explore-metrics?var-tsspec=${__series.name}&var-Metric=${__field.labels.__name__}"
            }
          ],
          "mappings": [],
          "thresholds": {
            "mode": "absolute",
            "steps": [
              {
                "color": "green",
                "value": null
              },
              {
                "color": "red",
                "value": 80
              }
            ]
          }
        },
        "overrides": []
      },
      "gridPos": {
        "h": 8,
        "w": 12,
        "x": 0,
        "y": 8
      },
      "id": 7,
      "options": {
        "legend": {
          "calcs": [],
          "displayMode": "list",
          "placement": "bottom",
          "showLegend": true
        },
        "tooltip": {
          "hideZeros": false,
          "mode": "single",
          "sort": "none"
        }
      },
      "pluginVersion": "11.5.2",
      "targets": [
        {
          "disableTextWrap": false,
          "editorMode": "builder",
          "expr": "postgres_database_active_time_seconds:rate1m{datname=\"mattermost_main\"}",
          "fullMetaSearch": false,
          "includeNullMetadata": true,
          "legendFormat": "__auto",
          "range": true,
          "refId": "A",
          "useBackend": false
        }
      ],
      "title": "Database active time rate",
      "type": "timeseries"
    },
    {
      "datasource": {
        "type": "prometheus",
        "uid": "prometheus"
      },
      "fieldConfig": {
        "defaults": {
          "color": {
            "mode": "palette-classic"
          },
          "custom": {
            "axisBorderShow": false,
            "axisCenteredZero": false,
            "axisColorMode": "text",
            "axisLabel": "",
            "axisPlacement": "auto",
            "barAlignment": 0,
            "barWidthFactor": 0.6,
            "drawStyle": "line",
            "fillOpacity": 0,
            "gradientMode": "none",
            "hideFrom": {
              "legend": false,
              "tooltip": false,
              "viz": false
            },
            "insertNulls": false,
            "lineInterpolation": "linear",
            "lineWidth": 1,
            "pointSize": 5,
            "scaleDistribution": {
              "type": "linear"
            },
            "showPoints": "auto",
            "spanNulls": false,
            "stacking": {
              "group": "A",
              "mode": "none"
            },
            "thresholdsStyle": {
              "mode": "off"
            }
          },
          "links": [
            {
              "targetBlank": true,
              "title": "",
              "url": "d/explore-metrics/explore-metrics?var-tsspec=${__series.name}&var-Metric=${__field.labels.__name__}"
            }
          ],
          "mappings": [],
          "thresholds": {
            "mode": "absolute",
            "steps": [
              {
                "color": "green",
                "value": null
              },
              {
                "color": "red",
                "value": 80
              }
            ]
          }
        },
        "overrides": []
      },
      "gridPos": {
        "h": 8,
        "w": 12,
        "x": 0,
        "y": 16
      },
      "id": 5,
      "options": {
        "legend": {
          "calcs": [],
          "displayMode": "list",
          "placement": "bottom",
          "showLegend": true
        },
        "tooltip": {
          "hideZeros": false,
          "mode": "single",
          "sort": "none"
        }
      },
      "pluginVersion": "11.5.2",
      "targets": [
        {
          "disableTextWrap": false,
          "editorMode": "builder",
          "expr": "container:loadtest_errors:rate1m",
          "fullMetaSearch": false,
          "includeNullMetadata": true,
          "legendFormat": "__auto",
          "range": true,
          "refId": "A",
          "useBackend": false
        }
      ],
      "title": "Loadtest error rate",
      "type": "timeseries"
    },
    {
      "datasource": {
        "type": "prometheus",
        "uid": "prometheus"
      },
      "fieldConfig": {
        "defaults": {
          "color": {
            "mode": "palette-classic"
          },
          "custom": {
            "axisBorderShow": false,
            "axisCenteredZero": false,
            "axisColorMode": "text",
            "axisLabel": "",
            "axisPlacement": "auto",
            "barAlignment": 0,
            "barWidthFactor": 0.6,
            "drawStyle": "line",
            "fillOpacity": 0,
            "gradientMode": "none",
            "hideFrom": {
              "legend": false,
              "tooltip": false,
              "viz": false
            },
            "insertNulls": false,
            "lineInterpolation": "linear",
            "lineWidth": 1,
            "pointSize": 5,
            "scaleDistribution": {
              "type": "linear"
            },
            "showPoints": "auto",
            "spanNulls": false,
            "stacking": {
              "group": "A",
              "mode": "none"
            },
            "thresholdsStyle": {
              "mode": "off"
            }
          },
          "links": [
            {
              "targetBlank": true,
              "title": "Explore correlated time series",
              "url": "d/explore-metrics/explore-metrics?var-tsspec=${__series.name}&var-Metric=${__field.labels.__name__}"
            }
          ],
          "mappings": [],
          "thresholds": {
            "mode": "absolute",
            "steps": [
              {
                "color": "green",
                "value": null
              },
              {
                "color": "red",
                "value": 80
              }
            ]
          }
        },
        "overrides": []
      },
      "gridPos": {
        "h": 8,
        "w": 12,
        "x": 0,
        "y": 24
      },
      "id": 6,
      "options": {
        "legend": {
          "calcs": [],
          "displayMode": "list",
          "placement": "bottom",
          "showLegend": true
        },
        "tooltip": {
          "hideZeros": false,
          "mode": "single",
          "sort": "none"
        }
      },
      "pluginVersion": "11.5.2",
      "targets": [
        {
          "disableTextWrap": false,
          "editorMode": "builder",
          "expr": "loadtest_latency:quantile95",
          "fullMetaSearch": false,
          "includeNullMetadata": true,
          "legendFormat": "__auto",
          "range": true,
          "refId": "A",
          "useBackend": false
        },
        {
          "datasource": {
            "type": "prometheus",
            "uid": "prometheus"
          },
          "disableTextWrap": false,
          "editorMode": "builder",
          "expr": "loadtest_latency:quantile50",
          "fullMetaSearch": false,
          "hide": false,
          "includeNullMetadata": true,
          "instant": false,
          "legendFormat": "__auto",
          "range": true,
          "refId": "B",
          "useBackend": false
        }
      ],
      "title": "Loadtest latency 95th and 50th percentiles",
      "type": "timeseries"
    },
    {
      "datasource": {
        "type": "prometheus",
        "uid": "prometheus"
      },
      "fieldConfig": {
        "defaults": {
          "color": {
            "mode": "palette-classic"
          },
          "custom": {
            "axisBorderShow": false,
            "axisCenteredZero": false,
            "axisColorMode": "text",
            "axisLabel": "",
            "axisPlacement": "auto",
            "barAlignment": 0,
            "barWidthFactor": 0.6,
            "drawStyle": "line",
            "fillOpacity": 0,
            "gradientMode": "none",
            "hideFrom": {
              "legend": false,
              "tooltip": false,
              "viz": false
            },
            "insertNulls": false,
            "lineInterpolation": "linear",
            "lineWidth": 1,
            "pointSize": 5,
            "scaleDistribution": {
              "type": "linear"
            },
            "showPoints": "auto",
            "spanNulls": false,
            "stacking": {
              "group": "A",
              "mode": "none"
            },
            "thresholdsStyle": {
              "mode": "off"
            }
          },
          "links": [
            {
              "targetBlank": true,
              "title": "Explore correlated time series",
              "url": "d/explore-metrics/explore-metrics?var-tsspec=${__series.name}&var-Metric=${__field.labels.__name__}"
            }
          ],
          "mappings": [],
          "thresholds": {
            "mode": "absolute",
            "steps": [
              {
                "color": "green",
                "value": null
              },
              {
                "color": "red",
                "value": 80
              }
            ]
          }
        },
        "overrides": []
      },
      "gridPos": {
        "h": 8,
        "w": 12,
        "x": 0,
        "y": 32
      },
      "id": 3,
      "options": {
        "legend": {
          "calcs": [],
          "displayMode": "list",
          "placement": "bottom",
          "showLegend": true
        },
        "tooltip": {
          "hideZeros": false,
          "mode": "single",
          "sort": "none"
        }
      },
      "pluginVersion": "11.5.2",
      "targets": [
        {
          "disableTextWrap": false,
          "editorMode": "builder",
          "expr": "rate(container_cpu_usage_seconds_total{namespace=\"mattermost\"}[$__rate_interval])",
          "fullMetaSearch": false,
          "includeNullMetadata": false,
          "legendFormat": "__auto",
          "range": true,
          "refId": "A",
          "useBackend": false
        }
      ],
      "title": "mattermost pod cpu load",
      "type": "timeseries"
    },
    {
      "datasource": {
        "type": "prometheus",
        "uid": "prometheus"
      },
      "fieldConfig": {
        "defaults": {
          "color": {
            "mode": "palette-classic"
          },
          "custom": {
            "axisBorderShow": false,
            "axisCenteredZero": false,
            "axisColorMode": "text",
            "axisLabel": "",
            "axisPlacement": "auto",
            "barAlignment": 0,
            "barWidthFactor": 0.6,
            "drawStyle": "line",
            "fillOpacity": 0,
            "gradientMode": "none",
            "hideFrom": {
              "legend": false,
              "tooltip": false,
              "viz": false
            },
            "insertNulls": false,
            "lineInterpolation": "linear",
            "lineWidth": 1,
            "pointSize": 5,
            "scaleDistribution": {
              "type": "linear"
            },
            "showPoints": "auto",
            "spanNulls": false,
            "stacking": {
              "group": "A",
              "mode": "none"
            },
            "thresholdsStyle": {
              "mode": "off"
            }
          },
          "links": [
            {
              "targetBlank": true,
              "title": "Explore correlated time series",
              "url": "d/explore-metrics/explore-metrics?var-tsspec=${__series.name}&var-Metric=${__field.labels.__name__}"
            }
          ],
          "mappings": [],
          "thresholds": {
            "mode": "absolute",
            "steps": [
              {
                "color": "green",
                "value": null
              },
              {
                "color": "red",
                "value": 80
              }
            ]
          }
        },
        "overrides": []
      },
      "gridPos": {
        "h": 8,
        "w": 12,
        "x": 0,
        "y": 40
      },
      "id": 1,
      "options": {
        "legend": {
          "calcs": [],
          "displayMode": "list",
          "placement": "bottom",
          "showLegend": true
        },
        "tooltip": {
          "hideZeros": false,
          "mode": "single",
          "sort": "none"
        }
      },
      "pluginVersion": "11.5.2",
      "targets": [
        {
          "datasource": {
            "type": "prometheus",
            "uid": "prometheus"
          },
          "disableTextWrap": false,
          "editorMode": "builder",
          "expr": "rate(loadtest_http_requests_total[$__rate_interval])",
          "fullMetaSearch": false,
          "hide": false,
          "includeNullMetadata": true,
          "instant": false,
          "legendFormat": "__auto",
          "range": true,
          "refId": "C",
          "useBackend": false
        }
      ],
      "title": "Loadtest request rates",
      "type": "timeseries"
    }
  ],
  "preload": false,
  "refresh": "",
  "schemaVersion": 40,
  "tags": [],
  "templating": {
    "list": []
  },
  "time": {
    "from": "now-6h",
    "to": "now"
  },
  "timepicker": {},
  "timezone": "browser",
  "title": "loadtest performance",
  "uid": "eegfdrv00ybr4d",
  "version": 2,
  "weekStart": ""
}
